[{
  "column_name": "id",
  "data_type": "uuid",
  "character_maximum_length": null,
  "is_nullable": "NO"
}, {
  "column_name": "title",
  "data_type": "character varying",
  "character_maximum_length": 500,
  "is_nullable": "NO"
}, {
  "column_name": "content",
  "data_type": "text",
  "character_maximum_length": null,
  "is_nullable": "NO"
}, {
  "column_name": "excerpt",
  "data_type": "character varying",
  "character_maximum_length": 1000,
  "is_nullable": "YES"
}, {
  "column_name": "slug",
  "data_type": "character varying",
  "character_maximum_length": 200,
  "is_nullable": "NO"
}, {
  "column_name": "featured_image",
  "data_type": "character varying",
  "character_maximum_length": null,
  "is_nullable": "YES"
}, {
  "column_name": "publish_date",
  "data_type": "timestamp without time zone",
  "character_maximum_length": null,
  "is_nullable": "NO"
}, {
  "column_name": "status",
  "data_type": "character varying",
  "character_maximum_length": 20,
  "is_nullable": "NO"
}, {
  "column_name": "author_id",
  "data_type": "character varying",
  "character_maximum_length": null,
  "is_nullable": "NO"
}, {
  "column_name": "seo_title",
  "data_type": "character varying",
  "character_maximum_length": 200,
  "is_nullable": "YES"
}, {
  "column_name": "meta_description",
  "data_type": "character varying",
  "character_maximum_length": 500,
  "is_nullable": "YES"
}, {
  "column_name": "focus_keyword",
  "data_type": "character varying",
  "character_maximum_length": 100,
  "is_nullable": "YES"
}, {
  "column_name": "job_company_name",
  "data_type": "character varying",
  "character_maximum_length": 200,
  "is_nullable": "YES"
}, {
  "column_name": "job_company_logo",
  "data_type": "character varying",
  "character_maximum_length": null,
  "is_nullable": "YES"
}, {
  "column_name": "job_location",
  "data_type": "character varying",
  "character_maximum_length": 200,
  "is_nullable": "YES"
}, {
  "column_name": "job_location_type",
  "data_type": "character varying",
  "character_maximum_length": 50,
  "is_nullable": "YES"
}, {
  "column_name": "job_salary_min",
  "data_type": "bigint",
  "character_maximum_length": null,
  "is_nullable": "YES"
}, {
  "column_name": "job_salary_max",
  "data_type": "bigint",
  "character_maximum_length": null,
  "is_nullable": "YES"
}, {
  "column_name": "job_salary_currency",
  "data_type": "character varying",
  "character_maximum_length": 10,
  "is_nullable": "YES"
}, {
  "column_name": "job_salary_period",
  "data_type": "character varying",
  "character_maximum_length": 20,
  "is_nullable": "YES"
}, {
  "column_name": "job_application_url",
  "data_type": "character varying",
  "character_maximum_length": null,
  "is_nullable": "YES"
}, {
  "column_name": "job_application_email",
  "data_type": "character varying",
  "character_maximum_length": null,
  "is_nullable": "YES"
}, {
  "column_name": "job_deadline",
  "data_type": "timestamp without time zone",
  "character_maximum_length": null,
  "is_nullable": "YES"
}, {
  "column_name": "job_skills",
  "data_type": "ARRAY",
  "character_maximum_length": null,
  "is_nullable": "YES"
}, {
  "column_name": "job_benefits",
  "data_type": "ARRAY",
  "character_maximum_length": null,
  "is_nullable": "YES"
}, {
  "column_name": "employment_type",
  "data_type": "character varying",
  "character_maximum_length": 50,
  "is_nullable": "YES"
}, {
  "column_name": "experience_level",
  "data_type": "character varying",
  "character_maximum_length": 50,
  "is_nullable": "YES"
}, {
  "column_name": "created_at",
  "data_type": "timestamp without time zone",
  "character_maximum_length": null,
  "is_nullable": "NO"
}, {
  "column_name": "updated_at",
  "data_type": "timestamp without time zone",
  "character_maximum_length": null,
  "is_nullable": "NO"
}, {
  "column_name": "job_company_website",
  "data_type": "character varying",
  "character_maximum_length": 500,
  "is_nullable": "YES"
}, {
  "column_name": "job_is_salary_negotiable",
  "data_type": "boolean",
  "character_maximum_length": null,
  "is_nullable": "YES"
}, {
  "column_name": "job_province_id",
  "data_type": "character varying",
  "character_maximum_length": 2,
  "is_nullable": "YES"
}, {
  "column_name": "job_regency_id",
  "data_type": "character varying",
  "character_maximum_length": 4,
  "is_nullable": "YES"
}, {
  "column_name": "job_district_id",
  "data_type": "character varying",
  "character_maximum_length": 6,
  "is_nullable": "YES"
}, {
  "column_name": "job_village_id",
  "data_type": "character varying",
  "character_maximum_length": 10,
  "is_nullable": "YES"
}, {
  "column_name": "job_address_detail",
  "data_type": "text",
  "character_maximum_length": null,
  "is_nullable": "YES"
}, {
  "column_name": "job_is_remote",
  "data_type": "boolean",
  "character_maximum_length": null,
  "is_nullable": "YES"
}, {
  "column_name": "job_is_hybrid",
  "data_type": "boolean",
  "character_maximum_length": null,
  "is_nullable": "YES"
}, {
  "column_name": "job_employment_type_id",
  "data_type": "uuid",
  "character_maximum_length": null,
  "is_nullable": "YES"
}, {
  "column_name": "job_experience_level_id",
  "data_type": "uuid",
  "character_maximum_length": null,
  "is_nullable": "YES"
}, {
  "column_name": "job_requirements",
  "data_type": "text",
  "character_maximum_length": null,
  "is_nullable": "YES"
}, {
  "column_name": "job_responsibilities",
  "data_type": "text",
  "character_maximum_length": null,
  "is_nullable": "YES"
}]
